automesh-0.3.7.dist-info/METADATA
automesh-0.3.7.dist-info/WHEEL
automesh-0.3.7.dist-info/licenses/LICENSE
automesh/__init__.py
automesh/automesh.cpython-313-x86_64-linux-gnu.so
automesh-0.3.7.dist-info/RECORD
