Metadata-Version: 2.4
Name: automesh
Version: 0.3.7
Classifier: License :: OSI Approved :: GNU General Public License v3 (GPLv3)
Classifier: Development Status :: 5 - Production/Stable
Classifier: Intended Audience :: Science/Research
Classifier: Programming Language :: Python
Classifier: Programming Language :: Rust
Classifier: Topic :: Scientific/Engineering
Requires-Dist: numpy
Requires-Dist: black ; extra == 'dev'
Requires-Dist: pdoc ; extra == 'dev'
Requires-Dist: pre-commit ; extra == 'dev'
Requires-Dist: pytest ; extra == 'dev'
Requires-Dist: pytest-cov ; extra == 'dev'
Requires-Dist: ruff ; extra == 'dev'
Provides-Extra: dev
License-File: LICENSE
Summary: automesh
Home-Page: https://autotwin.github.io/automesh
Author-email: "Chad B. Hovey" <chovey@sandia.gov>, "Michael R. Buche" <mrbuche@sandia.gov>
Requires-Python: >=3.10, <3.15
Project-URL: Documentation, https://automesh.readthedocs.io
Project-URL: Homepage, https://autotwin.github.io/automesh
Project-URL: Repository, https://github.com/autotwin/automesh
